{
  "config": {
    "camera": {
      "type": "perspective",
      "arguments": {
        "fov": 49.13434207760448
      },
      "transform": [
        [
          1.0,
          0.0,
          0.0,
          0.623726
        ],
        [
          0.0,
          -2.0000000000535112e-06,
          0.999999999998,
          -1.204741174107591
        ],
        [
          0.0,
          -0.999999999998,
          -2.0000000000535112e-06,
          -7.587052590532827
        ],
        [
          0.0,
          0.0,
          0.0,
          1.0
        ]
      ]
    },
    "films": [
      {
        "type": "image",
        "xresolution": 1200,
        "yresolution": 1200,
        "filename": "breakfast.exr",
        "scale": 12.0
      }
    ],
    "samplers": [
      {
        "type": "sobol",
        "pixelsamples": 4096
      }
    ],
    "integrator": {
      "type": "bdpt"
    }
  },
  "scene": {
    "textures": {
      "marble-tex": {
        "name": "marble-tex",
        "type": "color",
        "texture_class": "marble",
        "arguments": {
          "scale": 4.0
        }
      },
      "floor-tex": {
        "name": "floor-tex",
        "type": "color",
        "texture_class": "imagemap",
        "arguments": {
          "filename": "E:\\Pandora Scenes\\PBRT\\pbrt-v3-scenes\\breakfast\\textures/Seamless Marble Tiles.png"
        }
      },
      "floor-bump-tex": {
        "name": "floor-bump-tex",
        "type": "float",
        "texture_class": "imagemap",
        "arguments": {
          "filename": "E:\\Pandora Scenes\\PBRT\\pbrt-v3-scenes\\breakfast\\textures/Seamless Marble Tiles.png"
        }
      },
      "art-tex": {
        "name": "art-tex",
        "type": "color",
        "texture_class": "imagemap",
        "arguments": {
          "filename": "E:\\Pandora Scenes\\PBRT\\pbrt-v3-scenes\\breakfast\\textures/goldbuddha.png"
        }
      }
    },
    "light_sources": [
      {
        "type": "distant",
        "arguments": {
          "from": {
            "x": 9,
            "y": -4,
            "z": 9
          },
          "blackbody_temperature_kelvin": 5000.0,
          "blackbody_scale_factor": 10.0
        },
        "transform": [
          [
            1.0,
            0.0,
            0.0,
            0.0
          ],
          [
            0.0,
            1.0,
            0.0,
            0.0
          ],
          [
            0.0,
            0.0,
            1.0,
            0.0
          ],
          [
            0.0,
            0.0,
            0.0,
            1.0
          ]
        ]
      }
    ],
    "instance_templates": {},
    "instances": [],
    "non_instances_shapes": [
      {
        "type": "plymesh",
        "arguments": {
          "filename": "E:\\Pandora Scenes\\PBRT\\pbrt-v3-scenes\\breakfast\\geometry/Sphere_002_0000_m000.ply"
        },
        "transform": [
          [
            0.594083070755005,
            0.0,
            0.0,
            0.0
          ],
          [
            0.0,
            0.594083070755005,
            0.0,
            0.0
          ],
          [
            0.0,
            0.0,
            0.594083070755005,
            0.0
          ],
          [
            0.951433181762695,
            1.944540739059448,
            3.603615760803223,
            1.0
          ]
        ],
        "flip_normals": false,
        "material": {
          "type": "glass",
          "arguments": {
            "uroughness": 0.1,
            "vroughness": 0.1
          }
        },
        "area_light": null
      },
      {
        "type": "plymesh",
        "arguments": {
          "filename": "E:\\Pandora Scenes\\PBRT\\pbrt-v3-scenes\\breakfast\\geometry/Sphere_002_0000_m001.ply"
        },
        "transform": [
          [
            0.594083070755005,
            0.0,
            0.0,
            0.0
          ],
          [
            0.0,
            0.594083070755005,
            0.0,
            0.0
          ],
          [
            0.0,
            0.0,
            0.594083070755005,
            0.0
          ],
          [
            0.951433181762695,
            1.944540739059448,
            3.603615760803223,
            1.0
          ]
        ],
        "flip_normals": false,
        "material": {
          "type": "plastic",
          "arguments": {
            "Kd": {
              "r": 0.5,
              "g": 0.5,
              "b": 0.5
            },
            "Ks": {
              "r": 0.3,
              "g": 0.3,
              "b": 0.3
            },
            "roughness": 0.01
          }
        },
        "area_light": null
      },
      {
        "type": "plymesh",
        "arguments": {
          "filename": "E:\\Pandora Scenes\\PBRT\\pbrt-v3-scenes\\breakfast\\geometry/Sphere_001_0000_m000.ply"
        },
        "transform": [
          [
            0.594083070755005,
            0.0,
            0.0,
            0.0
          ],
          [
            0.0,
            0.594083070755005,
            0.0,
            0.0
          ],
          [
            0.0,
            0.0,
            0.594083070755005,
            0.0
          ],
          [
            -2.191241502761841,
            1.944540739059448,
            3.603615760803223,
            1.0
          ]
        ],
        "flip_normals": false,
        "material": {
          "type": "glass",
          "arguments": {
            "uroughness": 0.1,
            "vroughness": 0.1
          }
        },
        "area_light": null
      },
      {
        "type": "plymesh",
        "arguments": {
          "filename": "E:\\Pandora Scenes\\PBRT\\pbrt-v3-scenes\\breakfast\\geometry/Sphere_001_0000_m001.ply"
        },
        "transform": [
          [
            0.594083070755005,
            0.0,
            0.0,
            0.0
          ],
          [
            0.0,
            0.594083070755005,
            0.0,
            0.0
          ],
          [
            0.0,
            0.0,
            0.594083070755005,
            0.0
          ],
          [
            -2.191241502761841,
            1.944540739059448,
            3.603615760803223,
            1.0
          ]
        ],
        "flip_normals": false,
        "material": {
          "type": "plastic",
          "arguments": {
            "Kd": {
              "r": 0.5,
              "g": 0.5,
              "b": 0.5
            },
            "Ks": {
              "r": 0.3,
              "g": 0.3,
              "b": 0.3
            },
            "roughness": 0.01
          }
        },
        "area_light": null
      },
      {
        "type": "plymesh",
        "arguments": {
          "filename": "E:\\Pandora Scenes\\PBRT\\pbrt-v3-scenes\\breakfast\\geometry/Plane_006_0000_m000.ply"
        },
        "transform": [
          [
            2.3434739112854,
            0.0,
            0.0,
            0.0
          ],
          [
            0.0,
            1.242074131965637,
            0.0,
            0.0
          ],
          [
            0.0,
            0.0,
            1.0,
            0.0
          ],
          [
            5.146959781646729,
            0.61323481798172,
            1.960030198097229,
            1.0
          ]
        ],
        "flip_normals": false,
        "material": {
          "type": "matte",
          "arguments": {
            "Kd": {
              "r": 1.0,
              "g": 1.0,
              "b": 1.0
            }
          }
        },
        "area_light": null
      },
      {
        "type": "plymesh",
        "arguments": {
          "filename": "E:\\Pandora Scenes\\PBRT\\pbrt-v3-scenes\\breakfast\\geometry/Cube_007_0000_m000.ply"
        },
        "transform": [
          [
            1.0,
            0.0,
            0.0,
            0.0
          ],
          [
            0.0,
            1.0,
            0.0,
            0.0
          ],
          [
            0.0,
            0.0,
            1.0,
            0.0
          ],
          [
            -0.642285108566284,
            1.9039466381073,
            0.224622368812561,
            1.0
          ]
        ],
        "flip_normals": false,
        "material": {
          "type": "plastic",
          "arguments": {
            "Kd": {
              "r": 0.02,
              "g": 0.02,
              "b": 0.02
            },
            "Ks": {
              "r": 0.4,
              "g": 0.4,
              "b": 0.4
            },
            "roughness": 0.2
          }
        },
        "area_light": null
      },
      {
        "type": "plymesh",
        "arguments": {
          "filename": "E:\\Pandora Scenes\\PBRT\\pbrt-v3-scenes\\breakfast\\geometry/Circle_003_0000_m000.ply"
        },
        "transform": [
          [
            0.960156738758087,
            -0.279462069272995,
            0.0,
            0.0
          ],
          [
            0.279462069272995,
            0.960156738758087,
            0.0,
            0.0
          ],
          [
            0.0,
            0.0,
            1.0,
            0.0
          ],
          [
            -2.945224523544312,
            1.9320387840271,
            0.916272580623627,
            1.0
          ]
        ],
        "flip_normals": false,
        "material": {
          "type": "fourier",
          "arguments": {
            "bsdffile": "bsdfs/ceramic.bsdf"
          }
        },
        "area_light": null
      },
      {
        "type": "plymesh",
        "arguments": {
          "filename": "E:\\Pandora Scenes\\PBRT\\pbrt-v3-scenes\\breakfast\\geometry/Circle_003_0000_m001.ply"
        },
        "transform": [
          [
            0.960156738758087,
            -0.279462069272995,
            0.0,
            0.0
          ],
          [
            0.279462069272995,
            0.960156738758087,
            0.0,
            0.0
          ],
          [
            0.0,
            0.0,
            1.0,
            0.0
          ],
          [
            -2.945224523544312,
            1.9320387840271,
            0.916272580623627,
            1.0
          ]
        ],
        "flip_normals": false,
        "material": {
          "type": "metal",
          "arguments": {
            "eta": {
              "filename": "E:\\Pandora Scenes\\PBRT\\pbrt-v3-scenes\\breakfast\\spds/Ag.eta.spd"
            },
            "k": {
              "filename": "E:\\Pandora Scenes\\PBRT\\pbrt-v3-scenes\\breakfast\\spds/Ag.k.spd"
            },
            "roughness": 0.01
          }
        },
        "area_light": null
      },
      {
        "type": "plymesh",
        "arguments": {
          "filename": "E:\\Pandora Scenes\\PBRT\\pbrt-v3-scenes\\breakfast\\geometry/Plane_005_0000_m000.ply"
        },
        "transform": [
          [
            0.035585343837738,
            -0.028537899255753,
            1.224165e-09,
            0.0
          ],
          [
            0.028350833803415,
            0.0353520847857,
            -0.001094039995223,
            0.0
          ],
          [
            0.000684458995238,
            0.00085348758148,
            0.045316010713577,
            0.0
          ],
          [
            -3.022971153259277,
            2.051548004150391,
            0.937468111515045,
            1.0
          ]
        ],
        "flip_normals": false,
        "material": {
          "type": "matte",
          "arguments": {
            "Kd": {
              "r": 0.5,
              "g": 0.5,
              "b": 0.5
            },
            "sigma": 0.0
          }
        },
        "area_light": null
      },
      {
        "type": "plymesh",
        "arguments": {
          "filename": "E:\\Pandora Scenes\\PBRT\\pbrt-v3-scenes\\breakfast\\geometry/Circle_006_0000_m000.ply"
        },
        "transform": [
          [
            0.626249969005585,
            0.780904650688171,
            9.331852e-09,
            0.0
          ],
          [
            -0.780904650688171,
            0.626249969005585,
            -1.1636386e-08,
            0.0
          ],
          [
            0.0,
            0.0,
            1.001000046730042,
            0.0
          ],
          [
            -2.945224523544312,
            1.93203866481781,
            0.915794432163239,
            1.0
          ]
        ],
        "flip_normals": false,
        "material": {
          "type": "matte",
          "arguments": {
            "Kd": {
              "r": 0.5,
              "g": 0.5,
              "b": 0.5
            },
            "sigma": 0.0
          }
        },
        "area_light": null
      },
      {
        "type": "plymesh",
        "arguments": {
          "filename": "E:\\Pandora Scenes\\PBRT\\pbrt-v3-scenes\\breakfast\\geometry/Circle_006_0000_m001.ply"
        },
        "transform": [
          [
            0.626249969005585,
            0.780904650688171,
            9.331852e-09,
            0.0
          ],
          [
            -0.780904650688171,
            0.626249969005585,
            -1.1636386e-08,
            0.0
          ],
          [
            0.0,
            0.0,
            1.001000046730042,
            0.0
          ],
          [
            -2.945224523544312,
            1.93203866481781,
            0.915794432163239,
            1.0
          ]
        ],
        "flip_normals": false,
        "material": {
          "type": "metal",
          "arguments": {
            "eta": {
              "filename": "E:\\Pandora Scenes\\PBRT\\pbrt-v3-scenes\\breakfast\\spds/Ag.eta.spd"
            },
            "k": {
              "filename": "E:\\Pandora Scenes\\PBRT\\pbrt-v3-scenes\\breakfast\\spds/Ag.k.spd"
            },
            "roughness": 0.01
          }
        },
        "area_light": null
      },
      {
        "type": "plymesh",
        "arguments": {
          "filename": "E:\\Pandora Scenes\\PBRT\\pbrt-v3-scenes\\breakfast\\geometry/Circle_006_0000_m002.ply"
        },
        "transform": [
          [
            0.626249969005585,
            0.780904650688171,
            9.331852e-09,
            0.0
          ],
          [
            -0.780904650688171,
            0.626249969005585,
            -1.1636386e-08,
            0.0
          ],
          [
            0.0,
            0.0,
            1.001000046730042,
            0.0
          ],
          [
            -2.945224523544312,
            1.93203866481781,
            0.915794432163239,
            1.0
          ]
        ],
        "flip_normals": false,
        "material": {
          "type": "fourier",
          "arguments": {
            "bsdffile": "bsdfs/ceramic.bsdf"
          }
        },
        "area_light": null
      },
      {
        "type": "plymesh",
        "arguments": {
          "filename": "E:\\Pandora Scenes\\PBRT\\pbrt-v3-scenes\\breakfast\\geometry/Circle_002_0000_m000.ply"
        },
        "transform": [
          [
            0.960156738758087,
            -0.279462069272995,
            0.0,
            0.0
          ],
          [
            0.279462069272995,
            0.960156738758087,
            0.0,
            0.0
          ],
          [
            0.0,
            0.0,
            1.0,
            0.0
          ],
          [
            -1.041076183319092,
            1.123968362808228,
            0.916766405105591,
            1.0
          ]
        ],
        "flip_normals": false,
        "material": {
          "type": "fourier",
          "arguments": {
            "bsdffile": "bsdfs/ceramic.bsdf"
          }
        },
        "area_light": null
      },
      {
        "type": "plymesh",
        "arguments": {
          "filename": "E:\\Pandora Scenes\\PBRT\\pbrt-v3-scenes\\breakfast\\geometry/Circle_002_0000_m001.ply"
        },
        "transform": [
          [
            0.960156738758087,
            -0.279462069272995,
            0.0,
            0.0
          ],
          [
            0.279462069272995,
            0.960156738758087,
            0.0,
            0.0
          ],
          [
            0.0,
            0.0,
            1.0,
            0.0
          ],
          [
            -1.041076183319092,
            1.123968362808228,
            0.916766405105591,
            1.0
          ]
        ],
        "flip_normals": false,
        "material": {
          "type": "metal",
          "arguments": {
            "eta": {
              "filename": "E:\\Pandora Scenes\\PBRT\\pbrt-v3-scenes\\breakfast\\spds/Ag.eta.spd"
            },
            "k": {
              "filename": "E:\\Pandora Scenes\\PBRT\\pbrt-v3-scenes\\breakfast\\spds/Ag.k.spd"
            },
            "roughness": 0.01
          }
        },
        "area_light": null
      },
      {
        "type": "plymesh",
        "arguments": {
          "filename": "E:\\Pandora Scenes\\PBRT\\pbrt-v3-scenes\\breakfast\\geometry/Circle_000_0000_m000.ply"
        },
        "transform": [
          [
            0.626250028610229,
            0.780904591083527,
            -5.5991109e-08,
            0.0
          ],
          [
            -0.780904769897461,
            0.626250028610229,
            6.9818313e-08,
            0.0
          ],
          [
            0.0,
            0.0,
            1.001000046730042,
            0.0
          ],
          [
            -1.041076302528381,
            1.123968482017517,
            0.916288375854492,
            1.0
          ]
        ],
        "flip_normals": false,
        "material": {
          "type": "matte",
          "arguments": {
            "Kd": {
              "r": 0.5,
              "g": 0.5,
              "b": 0.5
            },
            "sigma": 0.0
          }
        },
        "area_light": null
      },
      {
        "type": "plymesh",
        "arguments": {
          "filename": "E:\\Pandora Scenes\\PBRT\\pbrt-v3-scenes\\breakfast\\geometry/Circle_000_0000_m001.ply"
        },
        "transform": [
          [
            0.626250028610229,
            0.780904591083527,
            -5.5991109e-08,
            0.0
          ],
          [
            -0.780904769897461,
            0.626250028610229,
            6.9818313e-08,
            0.0
          ],
          [
            0.0,
            0.0,
            1.001000046730042,
            0.0
          ],
          [
            -1.041076302528381,
            1.123968482017517,
            0.916288375854492,
            1.0
          ]
        ],
        "flip_normals": false,
        "material": {
          "type": "metal",
          "arguments": {
            "eta": {
              "filename": "E:\\Pandora Scenes\\PBRT\\pbrt-v3-scenes\\breakfast\\spds/Ag.eta.spd"
            },
            "k": {
              "filename": "E:\\Pandora Scenes\\PBRT\\pbrt-v3-scenes\\breakfast\\spds/Ag.k.spd"
            },
            "roughness": 0.01
          }
        },
        "area_light": null
      },
      {
        "type": "plymesh",
        "arguments": {
          "filename": "E:\\Pandora Scenes\\PBRT\\pbrt-v3-scenes\\breakfast\\geometry/Circle_000_0000_m002.ply"
        },
        "transform": [
          [
            0.626250028610229,
            0.780904591083527,
            -5.5991109e-08,
            0.0
          ],
          [
            -0.780904769897461,
            0.626250028610229,
            6.9818313e-08,
            0.0
          ],
          [
            0.0,
            0.0,
            1.001000046730042,
            0.0
          ],
          [
            -1.041076302528381,
            1.123968482017517,
            0.916288375854492,
            1.0
          ]
        ],
        "flip_normals": false,
        "material": {
          "type": "fourier",
          "arguments": {
            "bsdffile": "bsdfs/ceramic.bsdf"
          }
        },
        "area_light": null
      },
      {
        "type": "plymesh",
        "arguments": {
          "filename": "E:\\Pandora Scenes\\PBRT\\pbrt-v3-scenes\\breakfast\\geometry/Plane_004_0000_m000.ply"
        },
        "transform": [
          [
            0.035585347563028,
            -0.028537899255753,
            -2.487675e-09,
            0.0
          ],
          [
            0.028350839391351,
            0.0353520847857,
            -0.001094043022022,
            0.0
          ],
          [
            0.000684459053446,
            0.000853487523273,
            0.045316010713577,
            0.0
          ],
          [
            -1.118822932243347,
            1.243477940559387,
            0.937962055206299,
            1.0
          ]
        ],
        "flip_normals": false,
        "material": {
          "type": "matte",
          "arguments": {
            "Kd": {
              "r": 0.5,
              "g": 0.5,
              "b": 0.5
            },
            "sigma": 0.0
          }
        },
        "area_light": null
      },
      {
        "type": "plymesh",
        "arguments": {
          "filename": "E:\\Pandora Scenes\\PBRT\\pbrt-v3-scenes\\breakfast\\geometry/Teapot_0000_m000.ply"
        },
        "transform": [
          [
            0.127103701233864,
            -0.095074273645878,
            0.0,
            0.0
          ],
          [
            0.095074273645878,
            0.127103701233864,
            0.0,
            0.0
          ],
          [
            0.0,
            0.0,
            0.158727645874023,
            0.0
          ],
          [
            -0.769057631492615,
            1.948741316795349,
            0.896298587322235,
            1.0
          ]
        ],
        "flip_normals": false,
        "material": {
          "type": "fourier",
          "arguments": {
            "bsdffile": "bsdfs/ceramic.bsdf"
          }
        },
        "area_light": null
      },
      {
        "type": "plymesh",
        "arguments": {
          "filename": "E:\\Pandora Scenes\\PBRT\\pbrt-v3-scenes\\breakfast\\geometry/Cube_006_0000_m000.ply"
        },
        "transform": [
          [
            -1.026775749e-06,
            1.352859258651733,
            0.0,
            0.0
          ],
          [
            -1.352859258651733,
            -1.026775749e-06,
            0.0,
            0.0
          ],
          [
            0.0,
            0.0,
            1.352859258651733,
            0.0
          ],
          [
            -4.177764415740967,
            1.992996692657471,
            -0.191934317350388,
            1.0
          ]
        ],
        "flip_normals": false,
        "material": {
          "type": "plastic",
          "arguments": {
            "Kd": {
              "r": 0.5,
              "g": 0.5,
              "b": 0.5
            },
            "Ks": {
              "r": 0.3,
              "g": 0.3,
              "b": 0.3
            },
            "roughness": 0.01
          }
        },
        "area_light": null
      },
      {
        "type": "plymesh",
        "arguments": {
          "filename": "E:\\Pandora Scenes\\PBRT\\pbrt-v3-scenes\\breakfast\\geometry/Cylinder_005_0000_m000.ply"
        },
        "transform": [
          [
            -1.026775635e-06,
            1.352859139442444,
            1e-15,
            0.0
          ],
          [
            -1.352859258651733,
            -1.071740485e-06,
            -6.818131e-09,
            0.0
          ],
          [
            0.0,
            0.0,
            1.352859258651733,
            0.0
          ],
          [
            -3.780874729156494,
            1.99299681186676,
            -0.17792934179306,
            1.0
          ]
        ],
        "flip_normals": false,
        "material": {
          "type": "metal",
          "arguments": {
            "eta": {
              "filename": "E:\\Pandora Scenes\\PBRT\\pbrt-v3-scenes\\breakfast\\spds/Al.eta.spd"
            },
            "k": {
              "filename": "E:\\Pandora Scenes\\PBRT\\pbrt-v3-scenes\\breakfast\\spds/Al.k.spd"
            },
            "roughness": 0.01
          }
        },
        "area_light": null
      },
      {
        "type": "plymesh",
        "arguments": {
          "filename": "E:\\Pandora Scenes\\PBRT\\pbrt-v3-scenes\\breakfast\\geometry/Cylinder_005_0000_m001.ply"
        },
        "transform": [
          [
            -1.026775635e-06,
            1.352859139442444,
            1e-15,
            0.0
          ],
          [
            -1.352859258651733,
            -1.071740485e-06,
            -6.818131e-09,
            0.0
          ],
          [
            0.0,
            0.0,
            1.352859258651733,
            0.0
          ],
          [
            -3.780874729156494,
            1.99299681186676,
            -0.17792934179306,
            1.0
          ]
        ],
        "flip_normals": false,
        "material": {
          "type": "plastic",
          "arguments": {
            "Kd": {
              "r": 0.02,
              "g": 0.02,
              "b": 0.02
            },
            "Ks": {
              "r": 0.1,
              "g": 0.1,
              "b": 0.1
            },
            "roughness": 0.2
          }
        },
        "area_light": null
      },
      {
        "type": "plymesh",
        "arguments": {
          "filename": "E:\\Pandora Scenes\\PBRT\\pbrt-v3-scenes\\breakfast\\geometry/Cube_005_0000_m000.ply"
        },
        "transform": [
          [
            -1.352859258651733,
            2.053551498e-06,
            0.0,
            0.0
          ],
          [
            -2.053551498e-06,
            -1.352859258651733,
            0.0,
            0.0
          ],
          [
            0.0,
            0.0,
            1.352859258651733,
            0.0
          ],
          [
            -1.835080862045288,
            -0.233733206987381,
            -0.191934317350388,
            1.0
          ]
        ],
        "flip_normals": false,
        "material": {
          "type": "plastic",
          "arguments": {
            "Kd": {
              "r": 0.5,
              "g": 0.5,
              "b": 0.5
            },
            "Ks": {
              "r": 0.3,
              "g": 0.3,
              "b": 0.3
            },
            "roughness": 0.01
          }
        },
        "area_light": null
      },
      {
        "type": "plymesh",
        "arguments": {
          "filename": "E:\\Pandora Scenes\\PBRT\\pbrt-v3-scenes\\breakfast\\geometry/Cylinder_004_0000_m000.ply"
        },
        "transform": [
          [
            -1.352859258651733,
            2.041209427e-06,
            1.3636263e-08,
            0.0
          ],
          [
            -2.053551498e-06,
            -1.352859258651733,
            -1.8e-14,
            0.0
          ],
          [
            0.0,
            0.0,
            1.352859258651733,
            0.0
          ],
          [
            -1.83508038520813,
            0.163156718015671,
            -0.17792934179306,
            1.0
          ]
        ],
        "flip_normals": false,
        "material": {
          "type": "metal",
          "arguments": {
            "eta": {
              "filename": "E:\\Pandora Scenes\\PBRT\\pbrt-v3-scenes\\breakfast\\spds/Al.eta.spd"
            },
            "k": {
              "filename": "E:\\Pandora Scenes\\PBRT\\pbrt-v3-scenes\\breakfast\\spds/Al.k.spd"
            },
            "roughness": 0.01
          }
        },
        "area_light": null
      },
      {
        "type": "plymesh",
        "arguments": {
          "filename": "E:\\Pandora Scenes\\PBRT\\pbrt-v3-scenes\\breakfast\\geometry/Cylinder_004_0000_m001.ply"
        },
        "transform": [
          [
            -1.352859258651733,
            2.041209427e-06,
            1.3636263e-08,
            0.0
          ],
          [
            -2.053551498e-06,
            -1.352859258651733,
            -1.8e-14,
            0.0
          ],
          [
            0.0,
            0.0,
            1.352859258651733,
            0.0
          ],
          [
            -1.83508038520813,
            0.163156718015671,
            -0.17792934179306,
            1.0
          ]
        ],
        "flip_normals": false,
        "material": {
          "type": "plastic",
          "arguments": {
            "Kd": {
              "r": 0.02,
              "g": 0.02,
              "b": 0.02
            },
            "Ks": {
              "r": 0.1,
              "g": 0.1,
              "b": 0.1
            },
            "roughness": 0.2
          }
        },
        "area_light": null
      },
      {
        "type": "plymesh",
        "arguments": {
          "filename": "E:\\Pandora Scenes\\PBRT\\pbrt-v3-scenes\\breakfast\\geometry/Cube_004_0000_m000.ply"
        },
        "transform": [
          [
            -1.352859258651733,
            2.053551498e-06,
            0.0,
            0.0
          ],
          [
            -2.053551498e-06,
            -1.352859258651733,
            0.0,
            0.0
          ],
          [
            0.0,
            0.0,
            1.352859258651733,
            0.0
          ],
          [
            0.601839542388916,
            -0.233733206987381,
            -0.191934317350388,
            1.0
          ]
        ],
        "flip_normals": false,
        "material": {
          "type": "plastic",
          "arguments": {
            "Kd": {
              "r": 0.5,
              "g": 0.5,
              "b": 0.5
            },
            "Ks": {
              "r": 0.3,
              "g": 0.3,
              "b": 0.3
            },
            "roughness": 0.01
          }
        },
        "area_light": null
      },
      {
        "type": "plymesh",
        "arguments": {
          "filename": "E:\\Pandora Scenes\\PBRT\\pbrt-v3-scenes\\breakfast\\geometry/Cylinder_003_0000_m000.ply"
        },
        "transform": [
          [
            -1.352859258651733,
            2.053551498e-06,
            0.0,
            0.0
          ],
          [
            -2.053551498e-06,
            -1.352859258651733,
            0.0,
            0.0
          ],
          [
            0.0,
            0.0,
            1.352859258651733,
            0.0
          ],
          [
            0.601839959621429,
            0.163156718015671,
            -0.177929326891899,
            1.0
          ]
        ],
        "flip_normals": false,
        "material": {
          "type": "metal",
          "arguments": {
            "eta": {
              "filename": "E:\\Pandora Scenes\\PBRT\\pbrt-v3-scenes\\breakfast\\spds/Al.eta.spd"
            },
            "k": {
              "filename": "E:\\Pandora Scenes\\PBRT\\pbrt-v3-scenes\\breakfast\\spds/Al.k.spd"
            },
            "roughness": 0.01
          }
        },
        "area_light": null
      },
      {
        "type": "plymesh",
        "arguments": {
          "filename": "E:\\Pandora Scenes\\PBRT\\pbrt-v3-scenes\\breakfast\\geometry/Cylinder_003_0000_m001.ply"
        },
        "transform": [
          [
            -1.352859258651733,
            2.053551498e-06,
            0.0,
            0.0
          ],
          [
            -2.053551498e-06,
            -1.352859258651733,
            0.0,
            0.0
          ],
          [
            0.0,
            0.0,
            1.352859258651733,
            0.0
          ],
          [
            0.601839959621429,
            0.163156718015671,
            -0.177929326891899,
            1.0
          ]
        ],
        "flip_normals": false,
        "material": {
          "type": "plastic",
          "arguments": {
            "Kd": {
              "r": 0.02,
              "g": 0.02,
              "b": 0.02
            },
            "Ks": {
              "r": 0.1,
              "g": 0.1,
              "b": 0.1
            },
            "roughness": 0.2
          }
        },
        "area_light": null
      },
      {
        "type": "plymesh",
        "arguments": {
          "filename": "E:\\Pandora Scenes\\PBRT\\pbrt-v3-scenes\\breakfast\\geometry/Cube_003_0000_m000.ply"
        },
        "transform": [
          [
            -8.65502329e-07,
            -1.352859258651733,
            0.0,
            0.0
          ],
          [
            1.352859258651733,
            -8.65502329e-07,
            0.0,
            0.0
          ],
          [
            0.0,
            0.0,
            1.352859258651733,
            0.0
          ],
          [
            2.946556568145752,
            1.993371486663818,
            -0.191934317350388,
            1.0
          ]
        ],
        "flip_normals": false,
        "material": {
          "type": "plastic",
          "arguments": {
            "Kd": {
              "r": 0.5,
              "g": 0.5,
              "b": 0.5
            },
            "Ks": {
              "r": 0.3,
              "g": 0.3,
              "b": 0.3
            },
            "roughness": 0.01
          }
        },
        "area_light": null
      },
      {
        "type": "plymesh",
        "arguments": {
          "filename": "E:\\Pandora Scenes\\PBRT\\pbrt-v3-scenes\\breakfast\\geometry/Cylinder_002_0000_m000.ply"
        },
        "transform": [
          [
            -8.65502273e-07,
            -1.352859139442444,
            4e-15,
            0.0
          ],
          [
            1.352859139442444,
            -9.67373808e-07,
            -6.818131e-09,
            0.0
          ],
          [
            0.0,
            0.0,
            1.352859258651733,
            0.0
          ],
          [
            2.5496666431427,
            1.993371605873108,
            -0.17792934179306,
            1.0
          ]
        ],
        "flip_normals": false,
        "material": {
          "type": "metal",
          "arguments": {
            "eta": {
              "filename": "E:\\Pandora Scenes\\PBRT\\pbrt-v3-scenes\\breakfast\\spds/Al.eta.spd"
            },
            "k": {
              "filename": "E:\\Pandora Scenes\\PBRT\\pbrt-v3-scenes\\breakfast\\spds/Al.k.spd"
            },
            "roughness": 0.01
          }
        },
        "area_light": null
      },
      {
        "type": "plymesh",
        "arguments": {
          "filename": "E:\\Pandora Scenes\\PBRT\\pbrt-v3-scenes\\breakfast\\geometry/Cylinder_002_0000_m001.ply"
        },
        "transform": [
          [
            -8.65502273e-07,
            -1.352859139442444,
            4e-15,
            0.0
          ],
          [
            1.352859139442444,
            -9.67373808e-07,
            -6.818131e-09,
            0.0
          ],
          [
            0.0,
            0.0,
            1.352859258651733,
            0.0
          ],
          [
            2.5496666431427,
            1.993371605873108,
            -0.17792934179306,
            1.0
          ]
        ],
        "flip_normals": false,
        "material": {
          "type": "plastic",
          "arguments": {
            "Kd": {
              "r": 0.02,
              "g": 0.02,
              "b": 0.02
            },
            "Ks": {
              "r": 0.1,
              "g": 0.1,
              "b": 0.1
            },
            "roughness": 0.2
          }
        },
        "area_light": null
      },
      {
        "type": "plymesh",
        "arguments": {
          "filename": "E:\\Pandora Scenes\\PBRT\\pbrt-v3-scenes\\breakfast\\geometry/Cube_002_0000_m000.ply"
        },
        "transform": [
          [
            1.352859258651733,
            0.0,
            0.0,
            0.0
          ],
          [
            0.0,
            1.352859258651733,
            0.0,
            0.0
          ],
          [
            0.0,
            0.0,
            1.352859258651733,
            0.0
          ],
          [
            -1.886224508285522,
            3.869214057922363,
            -0.191934317350388,
            1.0
          ]
        ],
        "flip_normals": false,
        "material": {
          "type": "plastic",
          "arguments": {
            "Kd": {
              "r": 0.5,
              "g": 0.5,
              "b": 0.5
            },
            "Ks": {
              "r": 0.3,
              "g": 0.3,
              "b": 0.3
            },
            "roughness": 0.01
          }
        },
        "area_light": null
      },
      {
        "type": "plymesh",
        "arguments": {
          "filename": "E:\\Pandora Scenes\\PBRT\\pbrt-v3-scenes\\breakfast\\geometry/Cylinder_000_0000_m000.ply"
        },
        "transform": [
          [
            1.352859139442444,
            2.9349053e-07,
            -1.5476948e-08,
            0.0
          ],
          [
            0.0,
            1.352859258651733,
            0.0,
            0.0
          ],
          [
            0.0,
            0.0,
            1.352859258651733,
            0.0
          ],
          [
            -1.886224508285522,
            3.472323894500732,
            -0.17792934179306,
            1.0
          ]
        ],
        "flip_normals": false,
        "material": {
          "type": "metal",
          "arguments": {
            "eta": {
              "filename": "E:\\Pandora Scenes\\PBRT\\pbrt-v3-scenes\\breakfast\\spds/Al.eta.spd"
            },
            "k": {
              "filename": "E:\\Pandora Scenes\\PBRT\\pbrt-v3-scenes\\breakfast\\spds/Al.k.spd"
            },
            "roughness": 0.01
          }
        },
        "area_light": null
      },
      {
        "type": "plymesh",
        "arguments": {
          "filename": "E:\\Pandora Scenes\\PBRT\\pbrt-v3-scenes\\breakfast\\geometry/Cylinder_000_0000_m001.ply"
        },
        "transform": [
          [
            1.352859139442444,
            2.9349053e-07,
            -1.5476948e-08,
            0.0
          ],
          [
            0.0,
            1.352859258651733,
            0.0,
            0.0
          ],
          [
            0.0,
            0.0,
            1.352859258651733,
            0.0
          ],
          [
            -1.886224508285522,
            3.472323894500732,
            -0.17792934179306,
            1.0
          ]
        ],
        "flip_normals": false,
        "material": {
          "type": "plastic",
          "arguments": {
            "Kd": {
              "r": 0.02,
              "g": 0.02,
              "b": 0.02
            },
            "Ks": {
              "r": 0.1,
              "g": 0.1,
              "b": 0.1
            },
            "roughness": 0.2
          }
        },
        "area_light": null
      },
      {
        "type": "plymesh",
        "arguments": {
          "filename": "E:\\Pandora Scenes\\PBRT\\pbrt-v3-scenes\\breakfast\\geometry/Cube_001_0000_m000.ply"
        },
        "transform": [
          [
            1.0,
            0.0,
            0.0,
            0.0
          ],
          [
            0.0,
            1.0,
            0.0,
            0.0
          ],
          [
            0.0,
            0.0,
            1.0,
            0.0
          ],
          [
            -0.667227387428284,
            1.915051579475403,
            0.788318514823914,
            1.0
          ]
        ],
        "flip_normals": false,
        "material": {
          "type": "plastic",
          "arguments": {
            "Kd": {
              "name": "marble-tex"
            },
            "Ks": {
              "r": 0.3,
              "g": 0.3,
              "b": 0.3
            },
            "roughness": 0.1
          }
        },
        "area_light": null
      },
      {
        "type": "plymesh",
        "arguments": {
          "filename": "E:\\Pandora Scenes\\PBRT\\pbrt-v3-scenes\\breakfast\\geometry/Plane_0000_m000.ply"
        },
        "transform": [
          [
            1.02981162071228,
            0.0,
            0.0,
            0.0
          ],
          [
            0.0,
            1.0,
            0.0,
            0.0
          ],
          [
            0.0,
            0.0,
            1.0,
            0.0
          ],
          [
            -0.586363077163696,
            -0.048330441117287,
            -1.419957637786865,
            1.0
          ]
        ],
        "flip_normals": false,
        "material": {
          "type": "matte",
          "arguments": {
            "Kd": {
              "name": "floor-tex"
            },
            "sigma": 0.0
          }
        },
        "area_light": null
      },
      {
        "type": "plymesh",
        "arguments": {
          "filename": "E:\\Pandora Scenes\\PBRT\\pbrt-v3-scenes\\breakfast\\geometry/Plane_0000_m001.ply"
        },
        "transform": [
          [
            1.02981162071228,
            0.0,
            0.0,
            0.0
          ],
          [
            0.0,
            1.0,
            0.0,
            0.0
          ],
          [
            0.0,
            0.0,
            1.0,
            0.0
          ],
          [
            -0.586363077163696,
            -0.048330441117287,
            -1.419957637786865,
            1.0
          ]
        ],
        "flip_normals": false,
        "material": {
          "type": "matte",
          "arguments": {
            "Kd": {
              "r": 0.63999999,
              "g": 0.63999999,
              "b": 0.63999999
            },
            "sigma": 10.0
          }
        },
        "area_light": null
      },
      {
        "type": "plymesh",
        "arguments": {
          "filename": "E:\\Pandora Scenes\\PBRT\\pbrt-v3-scenes\\breakfast\\geometry/Cube_0000_m000.ply"
        },
        "transform": [
          [
            1.352859258651733,
            0.0,
            0.0,
            0.0
          ],
          [
            0.0,
            1.352859258651733,
            0.0,
            0.0
          ],
          [
            0.0,
            0.0,
            1.352859258651733,
            0.0
          ],
          [
            0.626897633075714,
            3.869214057922363,
            -0.191934317350388,
            1.0
          ]
        ],
        "flip_normals": false,
        "material": {
          "type": "plastic",
          "arguments": {
            "Kd": {
              "r": 0.5,
              "g": 0.5,
              "b": 0.5
            },
            "Ks": {
              "r": 0.3,
              "g": 0.3,
              "b": 0.3
            },
            "roughness": 0.01
          }
        },
        "area_light": null
      },
      {
        "type": "plymesh",
        "arguments": {
          "filename": "E:\\Pandora Scenes\\PBRT\\pbrt-v3-scenes\\breakfast\\geometry/Cylinder_001_0000_m000.ply"
        },
        "transform": [
          [
            1.352859258651733,
            0.0,
            0.0,
            0.0
          ],
          [
            0.0,
            1.352859258651733,
            0.0,
            0.0
          ],
          [
            0.0,
            0.0,
            1.352859258651733,
            0.0
          ],
          [
            0.626897633075714,
            3.472324132919312,
            -0.177929356694221,
            1.0
          ]
        ],
        "flip_normals": false,
        "material": {
          "type": "metal",
          "arguments": {
            "eta": {
              "filename": "E:\\Pandora Scenes\\PBRT\\pbrt-v3-scenes\\breakfast\\spds/Al.eta.spd"
            },
            "k": {
              "filename": "E:\\Pandora Scenes\\PBRT\\pbrt-v3-scenes\\breakfast\\spds/Al.k.spd"
            },
            "roughness": 0.01
          }
        },
        "area_light": null
      },
      {
        "type": "plymesh",
        "arguments": {
          "filename": "E:\\Pandora Scenes\\PBRT\\pbrt-v3-scenes\\breakfast\\geometry/Cylinder_001_0000_m001.ply"
        },
        "transform": [
          [
            1.352859258651733,
            0.0,
            0.0,
            0.0
          ],
          [
            0.0,
            1.352859258651733,
            0.0,
            0.0
          ],
          [
            0.0,
            0.0,
            1.352859258651733,
            0.0
          ],
          [
            0.626897633075714,
            3.472324132919312,
            -0.177929356694221,
            1.0
          ]
        ],
        "flip_normals": false,
        "material": {
          "type": "plastic",
          "arguments": {
            "Kd": {
              "r": 0.02,
              "g": 0.02,
              "b": 0.02
            },
            "Ks": {
              "r": 0.1,
              "g": 0.1,
              "b": 0.1
            },
            "roughness": 0.2
          }
        },
        "area_light": null
      },
      {
        "type": "plymesh",
        "arguments": {
          "filename": "E:\\Pandora Scenes\\PBRT\\pbrt-v3-scenes\\breakfast\\geometry/Plane_002_0000_m000.ply"
        },
        "transform": [
          [
            -0.212506517767906,
            -0.124359227716923,
            0.0,
            0.0
          ],
          [
            0.124359227716923,
            -0.212506517767906,
            0.0,
            0.0
          ],
          [
            0.0,
            0.0,
            0.273847609758377,
            0.0
          ],
          [
            -0.190780073404312,
            2.390382289886475,
            0.89889395236969,
            1.0
          ]
        ],
        "flip_normals": false,
        "material": {
          "type": "fourier",
          "arguments": {
            "bsdffile": "bsdfs/ceramic.bsdf"
          }
        },
        "area_light": null
      },
      {
        "type": "plymesh",
        "arguments": {
          "filename": "E:\\Pandora Scenes\\PBRT\\pbrt-v3-scenes\\breakfast\\geometry/Circle_013_0000_m000.ply"
        },
        "transform": [
          [
            -0.429397642612457,
            0.903115510940552,
            0.0,
            0.0
          ],
          [
            -0.903115510940552,
            -0.429397642612457,
            0.0,
            0.0
          ],
          [
            0.0,
            0.0,
            1.0,
            0.0
          ],
          [
            1.614856362342834,
            0.992693066596985,
            0.916766405105591,
            1.0
          ]
        ],
        "flip_normals": false,
        "material": {
          "type": "fourier",
          "arguments": {
            "bsdffile": "bsdfs/ceramic.bsdf"
          }
        },
        "area_light": null
      },
      {
        "type": "plymesh",
        "arguments": {
          "filename": "E:\\Pandora Scenes\\PBRT\\pbrt-v3-scenes\\breakfast\\geometry/Circle_013_0000_m001.ply"
        },
        "transform": [
          [
            -0.429397642612457,
            0.903115510940552,
            0.0,
            0.0
          ],
          [
            -0.903115510940552,
            -0.429397642612457,
            0.0,
            0.0
          ],
          [
            0.0,
            0.0,
            1.0,
            0.0
          ],
          [
            1.614856362342834,
            0.992693066596985,
            0.916766405105591,
            1.0
          ]
        ],
        "flip_normals": false,
        "material": {
          "type": "metal",
          "arguments": {
            "eta": {
              "filename": "E:\\Pandora Scenes\\PBRT\\pbrt-v3-scenes\\breakfast\\spds/Ag.eta.spd"
            },
            "k": {
              "filename": "E:\\Pandora Scenes\\PBRT\\pbrt-v3-scenes\\breakfast\\spds/Ag.k.spd"
            },
            "roughness": 0.01
          }
        },
        "area_light": null
      },
      {
        "type": "plymesh",
        "arguments": {
          "filename": "E:\\Pandora Scenes\\PBRT\\pbrt-v3-scenes\\breakfast\\geometry/Plane_003_0000_m000.ply"
        },
        "transform": [
          [
            -0.00233113206923,
            0.045555394142866,
            -3.25673e-10,
            0.0
          ],
          [
            -0.045256782323122,
            -0.002315851394087,
            -0.001094039296731,
            0.0
          ],
          [
            -0.001092611229979,
            -5.5911106756e-05,
            0.045316010713577,
            0.0
          ],
          [
            1.577243328094482,
            0.855170786380768,
            0.937961995601654,
            1.0
          ]
        ],
        "flip_normals": false,
        "material": {
          "type": "matte",
          "arguments": {
            "Kd": {
              "r": 0.5,
              "g": 0.5,
              "b": 0.5
            },
            "sigma": 0.0
          }
        },
        "area_light": null
      },
      {
        "type": "plymesh",
        "arguments": {
          "filename": "E:\\Pandora Scenes\\PBRT\\pbrt-v3-scenes\\breakfast\\geometry/Circle_005_0000_m000.ply"
        },
        "transform": [
          [
            -0.999691963195801,
            -0.051156841218472,
            2.983214e-08,
            0.0
          ],
          [
            0.051156841218472,
            -0.999691963195801,
            2.2374079e-08,
            0.0
          ],
          [
            0.0,
            0.0,
            1.001000046730042,
            0.0
          ],
          [
            1.614856362342834,
            0.992693066596985,
            0.916288316249847,
            1.0
          ]
        ],
        "flip_normals": false,
        "material": {
          "type": "matte",
          "arguments": {
            "Kd": {
              "r": 0.5,
              "g": 0.5,
              "b": 0.5
            },
            "sigma": 0.0
          }
        },
        "area_light": null
      },
      {
        "type": "plymesh",
        "arguments": {
          "filename": "E:\\Pandora Scenes\\PBRT\\pbrt-v3-scenes\\breakfast\\geometry/Circle_005_0000_m001.ply"
        },
        "transform": [
          [
            -0.999691963195801,
            -0.051156841218472,
            2.983214e-08,
            0.0
          ],
          [
            0.051156841218472,
            -0.999691963195801,
            2.2374079e-08,
            0.0
          ],
          [
            0.0,
            0.0,
            1.001000046730042,
            0.0
          ],
          [
            1.614856362342834,
            0.992693066596985,
            0.916288316249847,
            1.0
          ]
        ],
        "flip_normals": false,
        "material": {
          "type": "metal",
          "arguments": {
            "eta": {
              "filename": "E:\\Pandora Scenes\\PBRT\\pbrt-v3-scenes\\breakfast\\spds/Ag.eta.spd"
            },
            "k": {
              "filename": "E:\\Pandora Scenes\\PBRT\\pbrt-v3-scenes\\breakfast\\spds/Ag.k.spd"
            },
            "roughness": 0.01
          }
        },
        "area_light": null
      },
      {
        "type": "plymesh",
        "arguments": {
          "filename": "E:\\Pandora Scenes\\PBRT\\pbrt-v3-scenes\\breakfast\\geometry/Circle_005_0000_m002.ply"
        },
        "transform": [
          [
            -0.999691963195801,
            -0.051156841218472,
            2.983214e-08,
            0.0
          ],
          [
            0.051156841218472,
            -0.999691963195801,
            2.2374079e-08,
            0.0
          ],
          [
            0.0,
            0.0,
            1.001000046730042,
            0.0
          ],
          [
            1.614856362342834,
            0.992693066596985,
            0.916288316249847,
            1.0
          ]
        ],
        "flip_normals": false,
        "material": {
          "type": "fourier",
          "arguments": {
            "bsdffile": "bsdfs/ceramic.bsdf"
          }
        },
        "area_light": null
      },
      {
        "type": "plymesh",
        "arguments": {
          "filename": "E:\\Pandora Scenes\\PBRT\\pbrt-v3-scenes\\breakfast\\geometry/Canvas_-_Dry_Paint_Smudge_0000_m000.ply"
        },
        "transform": [
          [
            -3.847963809967041,
            -5.840955964e-06,
            0.0,
            0.0
          ],
          [
            5.840955964e-06,
            -3.847963809967041,
            0.0,
            0.0
          ],
          [
            0.0,
            0.0,
            3.847963809967041,
            0.0
          ],
          [
            -0.621391296386719,
            4.315586090087891,
            4.023087024688721,
            1.0
          ]
        ],
        "flip_normals": false,
        "material": {
          "type": "plastic",
          "arguments": {
            "Kd": {
              "name": "art-tex"
            },
            "Ks": {
              "r": 0.4,
              "g": 0.4,
              "b": 0.4
            },
            "roughness": 0.2
          }
        },
        "area_light": null
      },
      {
        "type": "plymesh",
        "arguments": {
          "filename": "E:\\Pandora Scenes\\PBRT\\pbrt-v3-scenes\\breakfast\\geometry/Mesh_024_0000_m000.ply"
        },
        "transform": [
          [
            -0.659938752651215,
            -6.87060322e-07,
            0.0,
            0.0
          ],
          [
            7.309162e-08,
            -0.070206344127655,
            0.0,
            0.0
          ],
          [
            0.0,
            0.0,
            0.070206344127655,
            0.0
          ],
          [
            -0.544918537139893,
            4.516851425170898,
            -1.281282067298889,
            1.0
          ]
        ],
        "flip_normals": false,
        "material": {
          "type": "matte",
          "arguments": {
            "Kd": {
              "r": 0.6,
              "g": 0.6,
              "b": 0.6
            },
            "sigma": 0.0
          }
        },
        "area_light": null
      },
      {
        "type": "trianglemesh",
        "arguments": {
          "filename": "c:\\Users\\Mathijs\\Documents\\GitHub\\pandora\\projects\\pbrt_importer\\python\\pbrt_meshes\\pbrt_mesh_0.bin"
        },
        "transform": [
          [
            1.0,
            0.0,
            0.0,
            0.0
          ],
          [
            0.0,
            1.0,
            0.0,
            0.0
          ],
          [
            0.0,
            0.0,
            1.0,
            0.0
          ],
          [
            0.0,
            0.0,
            0.0,
            1.0
          ]
        ],
        "flip_normals": false,
        "material": {
          "type": "matte",
          "arguments": {
            "Kd": {
              "r": 0.63999999,
              "g": 0.63999999,
              "b": 0.63999999
            },
            "sigma": 10.0
          }
        },
        "area_light": null
      },
      {
        "type": "trianglemesh",
        "arguments": {
          "filename": "c:\\Users\\Mathijs\\Documents\\GitHub\\pandora\\projects\\pbrt_importer\\python\\pbrt_meshes\\pbrt_mesh_1.bin"
        },
        "transform": [
          [
            1.0,
            0.0,
            0.0,
            0.0
          ],
          [
            0.0,
            1.0,
            0.0,
            0.0
          ],
          [
            0.0,
            0.0,
            1.0,
            0.0
          ],
          [
            0.0,
            0.0,
            0.0,
            1.0
          ]
        ],
        "flip_normals": false,
        "material": {
          "type": "matte",
          "arguments": {
            "Kd": {
              "r": 0.63999999,
              "g": 0.63999999,
              "b": 0.63999999
            },
            "sigma": 10.0
          }
        },
        "area_light": null
      }
    ]
  }
}